[
  {
    "slug": "srvi-update-2",
    "title": "SRVI Playtesting",
    "summary": "The new Survival Island gamemode has been built and will be being playtested soon.",
    "date": "2026-01-11"
  },
  {
    "slug": "new-website",
    "title": "New Website",
    "summary": "At the Team SMP, we've been working on a new website.",
    "date": "2025-09-17"
  },
  {
    "slug": "srvi-update-1",
    "title": "Update on SRVI",
    "summary": "The new Survival Island gamemode of the Team SMP has started being built.",
    "date": "2025-09-14"
  }
]
